CHANGELOG.md
sock.py
sock-0.5.0.dist-info/WHEEL
sock-0.5.0.dist-info/METADATA
sock-0.5.0.dist-info/RECORD
