Metadata-Version: 2.1
Name: sock
Version: 0.5.0
Summary: Small script to simplify network communication
License: MIT
Keywords: socket,telnet,network
Author: hellman
Requires-Python: >=3.4,<4.0
Classifier: Intended Audience :: Developers
Classifier: License :: OSI Approved :: MIT License
Classifier: Operating System :: Unix
Classifier: Programming Language :: Python :: 3
Classifier: Programming Language :: Python :: 3.4
Classifier: Programming Language :: Python :: 3.5
Classifier: Programming Language :: Python :: 3.6
Classifier: Programming Language :: Python :: 3.7
Classifier: Programming Language :: Python :: 3.8
Classifier: Topic :: System :: Networking
Project-URL: homepage, http://github.com/hellman/sock
